osim_utils/clients/crossref.py
osim_utils/clients/embl_data_warehouse.py
osim_utils/clients/epmc.py
osim_utils/clients/openalex.py
osim_utils/clients/ror.py
osim_utils/clients/sherpa.py
osim_utils/common.py
osim_utils/constants.py
osim_utils/decorators.py
osim_utils/exceptions.py
osim_utils/logger.py
osim_utils-0.6.5.dist-info/METADATA
osim_utils-0.6.5.dist-info/WHEEL
osim_utils-0.6.5.dist-info/RECORD
