Metadata-Version: 2.1
Name: osim-utils
Version: 0.6.5
Summary: 
Author: Your Name
Author-email: you@example.com
Requires-Python: >=3.10,<4.0
Classifier: Programming Language :: Python :: 3
Classifier: Programming Language :: Python :: 3.10
Classifier: Programming Language :: Python :: 3.11
Requires-Dist: python-json-logger (>=2.0.4,<3.0.0)
Requires-Dist: requests (>=2.28.2,<3.0.0)
Requires-Dist: requests-cache (>=1.1.0,<2.0.0)
